{
  "20350101": {
    "type": null,
    "name": "Різдвяний піст (Пилипівка) – від 15/28 листопада до Різдва Христового",
    "dayOfWeek": "пн",
    "shiftDaysFromEaster": -118
  },
  "20350102": {
    "type": "pist",
    "name": "Різдвяний піст (Пилипівка) – від 15/28 листопада до Різдва Христового",
    "dayOfWeek": "вт",
    "shiftDaysFromEaster": -117
  },
  "20350103": {
    "type": "pist",
    "name": "Різдвяний піст (Пилипівка) – від 15/28 листопада до Різдва Христового",
    "dayOfWeek": "ср",
    "shiftDaysFromEaster": -116
  },
  "20350104": {
    "type": "pist",
    "name": "Різдвяний піст (Пилипівка) – від 15/28 листопада до Різдва Христового",
    "dayOfWeek": "чт",
    "shiftDaysFromEaster": -115
  },
  "20350105": {
    "type": "pist",
    "name": "Різдвяний піст (Пилипівка) – від 15/28 листопада до Різдва Христового",
    "dayOfWeek": "пт",
    "shiftDaysFromEaster": -114
  },
  "20350106": {
    "type": "strohyjPist",
    "name": "Різдвяний піст (Пилипівка) – від 15/28 листопада до Різдва Христового",
    "dayOfWeek": "сб",
    "shiftDaysFromEaster": -113
  },
  "20350107": {
    "type": "zahalnytsya",
    "name": "Від Різдва Христового до святого Богоявлення",
    "dayOfWeek": "нд",
    "shiftDaysFromEaster": -112
  },
  "20350108": {
    "type": "zahalnytsya",
    "name": "Від Різдва Христового до святого Богоявлення",
    "dayOfWeek": "пн",
    "shiftDaysFromEaster": -111
  },
  "20350109": {
    "type": "zahalnytsya",
    "name": "Від Різдва Христового до святого Богоявлення",
    "dayOfWeek": "вт",
    "shiftDaysFromEaster": -110
  },
  "20350110": {
    "type": "zahalnytsya",
    "name": "Від Різдва Христового до святого Богоявлення",
    "dayOfWeek": "ср",
    "shiftDaysFromEaster": -109
  },
  "20350111": {
    "type": "zahalnytsya",
    "name": "Від Різдва Христового до святого Богоявлення",
    "dayOfWeek": "чт",
    "shiftDaysFromEaster": -108
  },
  "20350112": {
    "type": "zahalnytsya",
    "name": "Від Різдва Христового до святого Богоявлення",
    "dayOfWeek": "пт",
    "shiftDaysFromEaster": -107
  },
  "20350113": {
    "type": "zahalnytsya",
    "name": "Від Різдва Христового до святого Богоявлення",
    "dayOfWeek": "сб",
    "shiftDaysFromEaster": -106
  },
  "20350114": {
    "type": "zahalnytsya",
    "name": "Від Різдва Христового до святого Богоявлення",
    "dayOfWeek": "нд",
    "shiftDaysFromEaster": -105
  },
  "20350115": {
    "type": "zahalnytsya",
    "name": "Від Різдва Христового до святого Богоявлення",
    "dayOfWeek": "пн",
    "shiftDaysFromEaster": -104
  },
  "20350116": {
    "type": "zahalnytsya",
    "name": "Від Різдва Христового до святого Богоявлення",
    "dayOfWeek": "вт",
    "shiftDaysFromEaster": -103
  },
  "20350117": {
    "type": "zahalnytsya",
    "name": "Від Різдва Христового до святого Богоявлення",
    "dayOfWeek": "ср",
    "shiftDaysFromEaster": -102
  },
  "20350118": {
    "type": "strohyjPist",
    "name": null,
    "dayOfWeek": "чт",
    "shiftDaysFromEaster": -101
  },
  "20350119": {
    "type": "pist",
    "name": null,
    "dayOfWeek": "пт",
    "shiftDaysFromEaster": -100
  },
  "20350126": {
    "type": "pist",
    "name": null,
    "dayOfWeek": "пт",
    "shiftDaysFromEaster": -93
  },
  "20350202": {
    "type": "pist",
    "name": null,
    "dayOfWeek": "пт",
    "shiftDaysFromEaster": -86
  },
  "20350209": {
    "type": "pist",
    "name": null,
    "dayOfWeek": "пт",
    "shiftDaysFromEaster": -79
  },
  "20350216": {
    "type": "pist",
    "name": null,
    "dayOfWeek": "пт",
    "shiftDaysFromEaster": -72
  },
  "20350218": {
    "type": "zahalnytsya",
    "name": "Від Неділі про митаря і фарисея до Неділі про блудного сина",
    "dayOfWeek": "нд",
    "shiftDaysFromEaster": -70
  },
  "20350219": {
    "type": "zahalnytsya",
    "name": "Від Неділі про митаря і фарисея до Неділі про блудного сина",
    "dayOfWeek": "пн",
    "shiftDaysFromEaster": -69
  },
  "20350220": {
    "type": "zahalnytsya",
    "name": "Від Неділі про митаря і фарисея до Неділі про блудного сина",
    "dayOfWeek": "вт",
    "shiftDaysFromEaster": -68
  },
  "20350221": {
    "type": "zahalnytsya",
    "name": "Від Неділі про митаря і фарисея до Неділі про блудного сина",
    "dayOfWeek": "ср",
    "shiftDaysFromEaster": -67
  },
  "20350222": {
    "type": "zahalnytsya",
    "name": "Від Неділі про митаря і фарисея до Неділі про блудного сина",
    "dayOfWeek": "чт",
    "shiftDaysFromEaster": -66
  },
  "20350223": {
    "type": "zahalnytsya",
    "name": "Від Неділі про митаря і фарисея до Неділі про блудного сина",
    "dayOfWeek": "пт",
    "shiftDaysFromEaster": -65
  },
  "20350224": {
    "type": "zahalnytsya",
    "name": "Від Неділі про митаря і фарисея до Неділі про блудного сина",
    "dayOfWeek": "сб",
    "shiftDaysFromEaster": -64
  },
  "20350302": {
    "type": "pist",
    "name": null,
    "dayOfWeek": "пт",
    "shiftDaysFromEaster": -58
  },
  "20350309": {
    "type": "pist",
    "name": null,
    "dayOfWeek": "пт",
    "shiftDaysFromEaster": -51
  },
  "20350312": {
    "type": "strohyjPist",
    "name": "Великий піст (Чотиридесятниця) – від понеділка по Сиропусній неділі до празника Воскресення Христового",
    "dayOfWeek": "пн",
    "shiftDaysFromEaster": -48
  },
  "20350313": {
    "type": "pist",
    "name": "Великий піст (Чотиридесятниця) – від понеділка по Сиропусній неділі до празника Воскресення Христового",
    "dayOfWeek": "вт",
    "shiftDaysFromEaster": -47
  },
  "20350314": {
    "type": "pist",
    "name": "Великий піст (Чотиридесятниця) – від понеділка по Сиропусній неділі до празника Воскресення Христового",
    "dayOfWeek": "ср",
    "shiftDaysFromEaster": -46
  },
  "20350315": {
    "type": "pist",
    "name": "Великий піст (Чотиридесятниця) – від понеділка по Сиропусній неділі до празника Воскресення Христового",
    "dayOfWeek": "чт",
    "shiftDaysFromEaster": -45
  },
  "20350316": {
    "type": "pist",
    "name": "Великий піст (Чотиридесятниця) – від понеділка по Сиропусній неділі до празника Воскресення Христового",
    "dayOfWeek": "пт",
    "shiftDaysFromEaster": -44
  },
  "20350317": {
    "type": "pist",
    "name": "Великий піст (Чотиридесятниця) – від понеділка по Сиропусній неділі до празника Воскресення Христового",
    "dayOfWeek": "сб",
    "shiftDaysFromEaster": -43
  },
  "20350318": {
    "type": "pist",
    "name": "Великий піст (Чотиридесятниця) – від понеділка по Сиропусній неділі до празника Воскресення Христового",
    "dayOfWeek": "нд",
    "shiftDaysFromEaster": -42
  },
  "20350319": {
    "type": "pist",
    "name": "Великий піст (Чотиридесятниця) – від понеділка по Сиропусній неділі до празника Воскресення Христового",
    "dayOfWeek": "пн",
    "shiftDaysFromEaster": -41
  },
  "20350320": {
    "type": "pist",
    "name": "Великий піст (Чотиридесятниця) – від понеділка по Сиропусній неділі до празника Воскресення Христового",
    "dayOfWeek": "вт",
    "shiftDaysFromEaster": -40
  },
  "20350321": {
    "type": "pist",
    "name": "Великий піст (Чотиридесятниця) – від понеділка по Сиропусній неділі до празника Воскресення Христового",
    "dayOfWeek": "ср",
    "shiftDaysFromEaster": -39
  },
  "20350322": {
    "type": "pist",
    "name": "Великий піст (Чотиридесятниця) – від понеділка по Сиропусній неділі до празника Воскресення Христового",
    "dayOfWeek": "чт",
    "shiftDaysFromEaster": -38
  },
  "20350323": {
    "type": "pist",
    "name": "Великий піст (Чотиридесятниця) – від понеділка по Сиропусній неділі до празника Воскресення Христового",
    "dayOfWeek": "пт",
    "shiftDaysFromEaster": -37
  },
  "20350324": {
    "type": "pist",
    "name": "Великий піст (Чотиридесятниця) – від понеділка по Сиропусній неділі до празника Воскресення Христового",
    "dayOfWeek": "сб",
    "shiftDaysFromEaster": -36
  },
  "20350325": {
    "type": "pist",
    "name": "Великий піст (Чотиридесятниця) – від понеділка по Сиропусній неділі до празника Воскресення Христового",
    "dayOfWeek": "нд",
    "shiftDaysFromEaster": -35
  },
  "20350326": {
    "type": "pist",
    "name": "Великий піст (Чотиридесятниця) – від понеділка по Сиропусній неділі до празника Воскресення Христового",
    "dayOfWeek": "пн",
    "shiftDaysFromEaster": -34
  },
  "20350327": {
    "type": "pist",
    "name": "Великий піст (Чотиридесятниця) – від понеділка по Сиропусній неділі до празника Воскресення Христового",
    "dayOfWeek": "вт",
    "shiftDaysFromEaster": -33
  },
  "20350328": {
    "type": "pist",
    "name": "Великий піст (Чотиридесятниця) – від понеділка по Сиропусній неділі до празника Воскресення Христового",
    "dayOfWeek": "ср",
    "shiftDaysFromEaster": -32
  },
  "20350329": {
    "type": "pist",
    "name": "Великий піст (Чотиридесятниця) – від понеділка по Сиропусній неділі до празника Воскресення Христового",
    "dayOfWeek": "чт",
    "shiftDaysFromEaster": -31
  },
  "20350330": {
    "type": "pist",
    "name": "Великий піст (Чотиридесятниця) – від понеділка по Сиропусній неділі до празника Воскресення Христового",
    "dayOfWeek": "пт",
    "shiftDaysFromEaster": -30
  },
  "20350331": {
    "type": "pist",
    "name": "Великий піст (Чотиридесятниця) – від понеділка по Сиропусній неділі до празника Воскресення Христового",
    "dayOfWeek": "сб",
    "shiftDaysFromEaster": -29
  },
  "20350401": {
    "type": "pist",
    "name": "Великий піст (Чотиридесятниця) – від понеділка по Сиропусній неділі до празника Воскресення Христового",
    "dayOfWeek": "нд",
    "shiftDaysFromEaster": -28
  },
  "20350402": {
    "type": "pist",
    "name": "Великий піст (Чотиридесятниця) – від понеділка по Сиропусній неділі до празника Воскресення Христового",
    "dayOfWeek": "пн",
    "shiftDaysFromEaster": -27
  },
  "20350403": {
    "type": "pist",
    "name": "Великий піст (Чотиридесятниця) – від понеділка по Сиропусній неділі до празника Воскресення Христового",
    "dayOfWeek": "вт",
    "shiftDaysFromEaster": -26
  },
  "20350404": {
    "type": "pist",
    "name": "Великий піст (Чотиридесятниця) – від понеділка по Сиропусній неділі до празника Воскресення Христового",
    "dayOfWeek": "ср",
    "shiftDaysFromEaster": -25
  },
  "20350405": {
    "type": "pist",
    "name": "Великий піст (Чотиридесятниця) – від понеділка по Сиропусній неділі до празника Воскресення Христового",
    "dayOfWeek": "чт",
    "shiftDaysFromEaster": -24
  },
  "20350406": {
    "type": "pist",
    "name": "Великий піст (Чотиридесятниця) – від понеділка по Сиропусній неділі до празника Воскресення Христового",
    "dayOfWeek": "пт",
    "shiftDaysFromEaster": -23
  },
  "20350407": {
    "type": "pist",
    "name": "Великий піст (Чотиридесятниця) – від понеділка по Сиропусній неділі до празника Воскресення Христового",
    "dayOfWeek": "сб",
    "shiftDaysFromEaster": -22
  },
  "20350408": {
    "type": "pist",
    "name": "Великий піст (Чотиридесятниця) – від понеділка по Сиропусній неділі до празника Воскресення Христового",
    "dayOfWeek": "нд",
    "shiftDaysFromEaster": -21
  },
  "20350409": {
    "type": "pist",
    "name": "Великий піст (Чотиридесятниця) – від понеділка по Сиропусній неділі до празника Воскресення Христового",
    "dayOfWeek": "пн",
    "shiftDaysFromEaster": -20
  },
  "20350410": {
    "type": "pist",
    "name": "Великий піст (Чотиридесятниця) – від понеділка по Сиропусній неділі до празника Воскресення Христового",
    "dayOfWeek": "вт",
    "shiftDaysFromEaster": -19
  },
  "20350411": {
    "type": "pist",
    "name": "Великий піст (Чотиридесятниця) – від понеділка по Сиропусній неділі до празника Воскресення Христового",
    "dayOfWeek": "ср",
    "shiftDaysFromEaster": -18
  },
  "20350412": {
    "type": "pist",
    "name": "Великий піст (Чотиридесятниця) – від понеділка по Сиропусній неділі до празника Воскресення Христового",
    "dayOfWeek": "чт",
    "shiftDaysFromEaster": -17
  },
  "20350413": {
    "type": "pist",
    "name": "Великий піст (Чотиридесятниця) – від понеділка по Сиропусній неділі до празника Воскресення Христового",
    "dayOfWeek": "пт",
    "shiftDaysFromEaster": -16
  },
  "20350414": {
    "type": "pist",
    "name": "Великий піст (Чотиридесятниця) – від понеділка по Сиропусній неділі до празника Воскресення Христового",
    "dayOfWeek": "сб",
    "shiftDaysFromEaster": -15
  },
  "20350415": {
    "type": "pist",
    "name": "Великий піст (Чотиридесятниця) – від понеділка по Сиропусній неділі до празника Воскресення Христового",
    "dayOfWeek": "нд",
    "shiftDaysFromEaster": -14
  },
  "20350416": {
    "type": "pist",
    "name": "Великий піст (Чотиридесятниця) – від понеділка по Сиропусній неділі до празника Воскресення Христового",
    "dayOfWeek": "пн",
    "shiftDaysFromEaster": -13
  },
  "20350417": {
    "type": "pist",
    "name": "Великий піст (Чотиридесятниця) – від понеділка по Сиропусній неділі до празника Воскресення Христового",
    "dayOfWeek": "вт",
    "shiftDaysFromEaster": -12
  },
  "20350418": {
    "type": "pist",
    "name": "Великий піст (Чотиридесятниця) – від понеділка по Сиропусній неділі до празника Воскресення Христового",
    "dayOfWeek": "ср",
    "shiftDaysFromEaster": -11
  },
  "20350419": {
    "type": "pist",
    "name": "Великий піст (Чотиридесятниця) – від понеділка по Сиропусній неділі до празника Воскресення Христового",
    "dayOfWeek": "чт",
    "shiftDaysFromEaster": -10
  },
  "20350420": {
    "type": "pist",
    "name": "Великий піст (Чотиридесятниця) – від понеділка по Сиропусній неділі до празника Воскресення Христового",
    "dayOfWeek": "пт",
    "shiftDaysFromEaster": -9
  },
  "20350421": {
    "type": "pist",
    "name": "Великий піст (Чотиридесятниця) – від понеділка по Сиропусній неділі до празника Воскресення Христового",
    "dayOfWeek": "сб",
    "shiftDaysFromEaster": -8
  },
  "20350422": {
    "type": "pist",
    "name": "Великий піст (Чотиридесятниця) – від понеділка по Сиропусній неділі до празника Воскресення Христового",
    "dayOfWeek": "нд",
    "shiftDaysFromEaster": -7
  },
  "20350423": {
    "type": "pist",
    "name": "Великий піст (Чотиридесятниця) – від понеділка по Сиропусній неділі до празника Воскресення Христового",
    "dayOfWeek": "пн",
    "shiftDaysFromEaster": -6
  },
  "20350424": {
    "type": "pist",
    "name": "Великий піст (Чотиридесятниця) – від понеділка по Сиропусній неділі до празника Воскресення Христового",
    "dayOfWeek": "вт",
    "shiftDaysFromEaster": -5
  },
  "20350425": {
    "type": "pist",
    "name": "Великий піст (Чотиридесятниця) – від понеділка по Сиропусній неділі до празника Воскресення Христового",
    "dayOfWeek": "ср",
    "shiftDaysFromEaster": -4
  },
  "20350426": {
    "type": "pist",
    "name": "Великий піст (Чотиридесятниця) – від понеділка по Сиропусній неділі до празника Воскресення Христового",
    "dayOfWeek": "чт",
    "shiftDaysFromEaster": -3
  },
  "20350427": {
    "type": "strohyjPist",
    "name": "Великий піст (Чотиридесятниця) – від понеділка по Сиропусній неділі до празника Воскресення Христового",
    "dayOfWeek": "пт",
    "shiftDaysFromEaster": -2
  },
  "20350428": {
    "type": "pist",
    "name": "Великий піст (Чотиридесятниця) – від понеділка по Сиропусній неділі до празника Воскресення Христового",
    "dayOfWeek": "сб",
    "shiftDaysFromEaster": -1
  },
  "20350429": {
    "type": "zahalnytsya",
    "name": "У Світлий тиждень Пасхи",
    "dayOfWeek": "нд",
    "shiftDaysFromEaster": 0
  },
  "20350430": {
    "type": "zahalnytsya",
    "name": "У Світлий тиждень Пасхи",
    "dayOfWeek": "пн",
    "shiftDaysFromEaster": 1
  },
  "20350501": {
    "type": "zahalnytsya",
    "name": "У Світлий тиждень Пасхи",
    "dayOfWeek": "вт",
    "shiftDaysFromEaster": 2
  },
  "20350502": {
    "type": "zahalnytsya",
    "name": "У Світлий тиждень Пасхи",
    "dayOfWeek": "ср",
    "shiftDaysFromEaster": 3
  },
  "20350503": {
    "type": "zahalnytsya",
    "name": "У Світлий тиждень Пасхи",
    "dayOfWeek": "чт",
    "shiftDaysFromEaster": 4
  },
  "20350504": {
    "type": "zahalnytsya",
    "name": "У Світлий тиждень Пасхи",
    "dayOfWeek": "пт",
    "shiftDaysFromEaster": 5
  },
  "20350505": {
    "type": "zahalnytsya",
    "name": "У Світлий тиждень Пасхи",
    "dayOfWeek": "сб",
    "shiftDaysFromEaster": 6
  },
  "20350511": {
    "type": "pist",
    "name": null,
    "dayOfWeek": "пт",
    "shiftDaysFromEaster": 12
  },
  "20350518": {
    "type": "pist",
    "name": null,
    "dayOfWeek": "пт",
    "shiftDaysFromEaster": 19
  },
  "20350525": {
    "type": "pist",
    "name": null,
    "dayOfWeek": "пт",
    "shiftDaysFromEaster": 26
  },
  "20350601": {
    "type": "pist",
    "name": null,
    "dayOfWeek": "пт",
    "shiftDaysFromEaster": 33
  },
  "20350608": {
    "type": "pist",
    "name": null,
    "dayOfWeek": "пт",
    "shiftDaysFromEaster": 40
  },
  "20350615": {
    "type": "pist",
    "name": null,
    "dayOfWeek": "пт",
    "shiftDaysFromEaster": 47
  },
  "20350617": {
    "type": "zahalnytsya",
    "name": "Від Зіслання Святого Духа до Неділі всіх святих",
    "dayOfWeek": "нд",
    "shiftDaysFromEaster": 49
  },
  "20350618": {
    "type": "zahalnytsya",
    "name": "Від Зіслання Святого Духа до Неділі всіх святих",
    "dayOfWeek": "пн",
    "shiftDaysFromEaster": 50
  },
  "20350619": {
    "type": "zahalnytsya",
    "name": "Від Зіслання Святого Духа до Неділі всіх святих",
    "dayOfWeek": "вт",
    "shiftDaysFromEaster": 51
  },
  "20350620": {
    "type": "zahalnytsya",
    "name": "Від Зіслання Святого Духа до Неділі всіх святих",
    "dayOfWeek": "ср",
    "shiftDaysFromEaster": 52
  },
  "20350621": {
    "type": "zahalnytsya",
    "name": "Від Зіслання Святого Духа до Неділі всіх святих",
    "dayOfWeek": "чт",
    "shiftDaysFromEaster": 53
  },
  "20350622": {
    "type": "zahalnytsya",
    "name": "Від Зіслання Святого Духа до Неділі всіх святих",
    "dayOfWeek": "пт",
    "shiftDaysFromEaster": 54
  },
  "20350623": {
    "type": "zahalnytsya",
    "name": "Від Зіслання Святого Духа до Неділі всіх святих",
    "dayOfWeek": "сб",
    "shiftDaysFromEaster": 55
  },
  "20350625": {
    "type": "pist",
    "name": "Петрів піст (Петрівка) – від Неділі всіх святих до празника святих Петра і Павла",
    "dayOfWeek": "пн",
    "shiftDaysFromEaster": 57
  },
  "20350626": {
    "type": "pist",
    "name": "Петрів піст (Петрівка) – від Неділі всіх святих до празника святих Петра і Павла",
    "dayOfWeek": "вт",
    "shiftDaysFromEaster": 58
  },
  "20350627": {
    "type": "pist",
    "name": "Петрів піст (Петрівка) – від Неділі всіх святих до празника святих Петра і Павла",
    "dayOfWeek": "ср",
    "shiftDaysFromEaster": 59
  },
  "20350628": {
    "type": "pist",
    "name": "Петрів піст (Петрівка) – від Неділі всіх святих до празника святих Петра і Павла",
    "dayOfWeek": "чт",
    "shiftDaysFromEaster": 60
  },
  "20350629": {
    "type": "pist",
    "name": "Петрів піст (Петрівка) – від Неділі всіх святих до празника святих Петра і Павла",
    "dayOfWeek": "пт",
    "shiftDaysFromEaster": 61
  },
  "20350630": {
    "type": "pist",
    "name": "Петрів піст (Петрівка) – від Неділі всіх святих до празника святих Петра і Павла",
    "dayOfWeek": "сб",
    "shiftDaysFromEaster": 62
  },
  "20350701": {
    "type": "pist",
    "name": "Петрів піст (Петрівка) – від Неділі всіх святих до празника святих Петра і Павла",
    "dayOfWeek": "нд",
    "shiftDaysFromEaster": 63
  },
  "20350702": {
    "type": "pist",
    "name": "Петрів піст (Петрівка) – від Неділі всіх святих до празника святих Петра і Павла",
    "dayOfWeek": "пн",
    "shiftDaysFromEaster": 64
  },
  "20350703": {
    "type": "pist",
    "name": "Петрів піст (Петрівка) – від Неділі всіх святих до празника святих Петра і Павла",
    "dayOfWeek": "вт",
    "shiftDaysFromEaster": 65
  },
  "20350704": {
    "type": "pist",
    "name": "Петрів піст (Петрівка) – від Неділі всіх святих до празника святих Петра і Павла",
    "dayOfWeek": "ср",
    "shiftDaysFromEaster": 66
  },
  "20350705": {
    "type": "pist",
    "name": "Петрів піст (Петрівка) – від Неділі всіх святих до празника святих Петра і Павла",
    "dayOfWeek": "чт",
    "shiftDaysFromEaster": 67
  },
  "20350706": {
    "type": null,
    "name": "Петрів піст (Петрівка) – від Неділі всіх святих до празника святих Петра і Павла",
    "dayOfWeek": "пт",
    "shiftDaysFromEaster": 68
  },
  "20350707": {
    "type": "pist",
    "name": "Петрів піст (Петрівка) – від Неділі всіх святих до празника святих Петра і Павла",
    "dayOfWeek": "сб",
    "shiftDaysFromEaster": 69
  },
  "20350708": {
    "type": "pist",
    "name": "Петрів піст (Петрівка) – від Неділі всіх святих до празника святих Петра і Павла",
    "dayOfWeek": "нд",
    "shiftDaysFromEaster": 70
  },
  "20350709": {
    "type": "pist",
    "name": "Петрів піст (Петрівка) – від Неділі всіх святих до празника святих Петра і Павла",
    "dayOfWeek": "пн",
    "shiftDaysFromEaster": 71
  },
  "20350710": {
    "type": "pist",
    "name": "Петрів піст (Петрівка) – від Неділі всіх святих до празника святих Петра і Павла",
    "dayOfWeek": "вт",
    "shiftDaysFromEaster": 72
  },
  "20350711": {
    "type": "pist",
    "name": "Петрів піст (Петрівка) – від Неділі всіх святих до празника святих Петра і Павла",
    "dayOfWeek": "ср",
    "shiftDaysFromEaster": 73
  },
  "20350713": {
    "type": "pist",
    "name": null,
    "dayOfWeek": "пт",
    "shiftDaysFromEaster": 75
  },
  "20350720": {
    "type": "pist",
    "name": null,
    "dayOfWeek": "пт",
    "shiftDaysFromEaster": 82
  },
  "20350727": {
    "type": "pist",
    "name": null,
    "dayOfWeek": "пт",
    "shiftDaysFromEaster": 89
  },
  "20350803": {
    "type": "pist",
    "name": null,
    "dayOfWeek": "пт",
    "shiftDaysFromEaster": 96
  },
  "20350810": {
    "type": "pist",
    "name": null,
    "dayOfWeek": "пт",
    "shiftDaysFromEaster": 103
  },
  "20350814": {
    "type": "pist",
    "name": "Успенський піст (Спасівка) – від 1/14 серпня до празника Успення Пресвятої Богородиці",
    "dayOfWeek": "вт",
    "shiftDaysFromEaster": 107
  },
  "20350815": {
    "type": "pist",
    "name": "Успенський піст (Спасівка) – від 1/14 серпня до празника Успення Пресвятої Богородиці",
    "dayOfWeek": "ср",
    "shiftDaysFromEaster": 108
  },
  "20350816": {
    "type": "pist",
    "name": "Успенський піст (Спасівка) – від 1/14 серпня до празника Успення Пресвятої Богородиці",
    "dayOfWeek": "чт",
    "shiftDaysFromEaster": 109
  },
  "20350817": {
    "type": "pist",
    "name": "Успенський піст (Спасівка) – від 1/14 серпня до празника Успення Пресвятої Богородиці",
    "dayOfWeek": "пт",
    "shiftDaysFromEaster": 110
  },
  "20350818": {
    "type": "pist",
    "name": "Успенський піст (Спасівка) – від 1/14 серпня до празника Успення Пресвятої Богородиці",
    "dayOfWeek": "сб",
    "shiftDaysFromEaster": 111
  },
  "20350819": {
    "type": null,
    "name": "Успенський піст (Спасівка) – від 1/14 серпня до празника Успення Пресвятої Богородиці",
    "dayOfWeek": "нд",
    "shiftDaysFromEaster": 112
  },
  "20350820": {
    "type": "pist",
    "name": "Успенський піст (Спасівка) – від 1/14 серпня до празника Успення Пресвятої Богородиці",
    "dayOfWeek": "пн",
    "shiftDaysFromEaster": 113
  },
  "20350821": {
    "type": "pist",
    "name": "Успенський піст (Спасівка) – від 1/14 серпня до празника Успення Пресвятої Богородиці",
    "dayOfWeek": "вт",
    "shiftDaysFromEaster": 114
  },
  "20350822": {
    "type": "pist",
    "name": "Успенський піст (Спасівка) – від 1/14 серпня до празника Успення Пресвятої Богородиці",
    "dayOfWeek": "ср",
    "shiftDaysFromEaster": 115
  },
  "20350823": {
    "type": "pist",
    "name": "Успенський піст (Спасівка) – від 1/14 серпня до празника Успення Пресвятої Богородиці",
    "dayOfWeek": "чт",
    "shiftDaysFromEaster": 116
  },
  "20350824": {
    "type": null,
    "name": "Успенський піст (Спасівка) – від 1/14 серпня до празника Успення Пресвятої Богородиці",
    "dayOfWeek": "пт",
    "shiftDaysFromEaster": 117
  },
  "20350825": {
    "type": "pist",
    "name": "Успенський піст (Спасівка) – від 1/14 серпня до празника Успення Пресвятої Богородиці",
    "dayOfWeek": "сб",
    "shiftDaysFromEaster": 118
  },
  "20350826": {
    "type": "pist",
    "name": "Успенський піст (Спасівка) – від 1/14 серпня до празника Успення Пресвятої Богородиці",
    "dayOfWeek": "нд",
    "shiftDaysFromEaster": 119
  },
  "20350827": {
    "type": "pist",
    "name": "Успенський піст (Спасівка) – від 1/14 серпня до празника Успення Пресвятої Богородиці",
    "dayOfWeek": "пн",
    "shiftDaysFromEaster": 120
  },
  "20350831": {
    "type": "pist",
    "name": null,
    "dayOfWeek": "пт",
    "shiftDaysFromEaster": 124
  },
  "20350907": {
    "type": "pist",
    "name": null,
    "dayOfWeek": "пт",
    "shiftDaysFromEaster": 131
  },
  "20350911": {
    "type": "strohyjPist",
    "name": null,
    "dayOfWeek": "вт",
    "shiftDaysFromEaster": 135
  },
  "20350914": {
    "type": "pist",
    "name": null,
    "dayOfWeek": "пт",
    "shiftDaysFromEaster": 138
  },
  "20350927": {
    "type": "strohyjPist",
    "name": null,
    "dayOfWeek": "чт",
    "shiftDaysFromEaster": 151
  },
  "20350928": {
    "type": "pist",
    "name": null,
    "dayOfWeek": "пт",
    "shiftDaysFromEaster": 152
  },
  "20351005": {
    "type": "pist",
    "name": null,
    "dayOfWeek": "пт",
    "shiftDaysFromEaster": 159
  },
  "20351012": {
    "type": "pist",
    "name": null,
    "dayOfWeek": "пт",
    "shiftDaysFromEaster": 166
  },
  "20351019": {
    "type": "pist",
    "name": null,
    "dayOfWeek": "пт",
    "shiftDaysFromEaster": 173
  },
  "20351026": {
    "type": "pist",
    "name": null,
    "dayOfWeek": "пт",
    "shiftDaysFromEaster": 180
  },
  "20351102": {
    "type": "pist",
    "name": null,
    "dayOfWeek": "пт",
    "shiftDaysFromEaster": 187
  },
  "20351109": {
    "type": "pist",
    "name": null,
    "dayOfWeek": "пт",
    "shiftDaysFromEaster": 194
  },
  "20351116": {
    "type": "pist",
    "name": null,
    "dayOfWeek": "пт",
    "shiftDaysFromEaster": 201
  },
  "20351123": {
    "type": "pist",
    "name": null,
    "dayOfWeek": "пт",
    "shiftDaysFromEaster": 208
  },
  "20351128": {
    "type": "pist",
    "name": "Різдвяний піст (Пилипівка) – від 15/28 листопада до Різдва Христового",
    "dayOfWeek": "ср",
    "shiftDaysFromEaster": 213
  },
  "20351129": {
    "type": "pist",
    "name": "Різдвяний піст (Пилипівка) – від 15/28 листопада до Різдва Христового",
    "dayOfWeek": "чт",
    "shiftDaysFromEaster": 214
  },
  "20351130": {
    "type": "pist",
    "name": "Різдвяний піст (Пилипівка) – від 15/28 листопада до Різдва Христового",
    "dayOfWeek": "пт",
    "shiftDaysFromEaster": 215
  },
  "20351201": {
    "type": "pist",
    "name": "Різдвяний піст (Пилипівка) – від 15/28 листопада до Різдва Христового",
    "dayOfWeek": "сб",
    "shiftDaysFromEaster": 216
  },
  "20351202": {
    "type": "pist",
    "name": "Різдвяний піст (Пилипівка) – від 15/28 листопада до Різдва Христового",
    "dayOfWeek": "нд",
    "shiftDaysFromEaster": 217
  },
  "20351203": {
    "type": "pist",
    "name": "Різдвяний піст (Пилипівка) – від 15/28 листопада до Різдва Христового",
    "dayOfWeek": "пн",
    "shiftDaysFromEaster": 218
  },
  "20351204": {
    "type": null,
    "name": "Різдвяний піст (Пилипівка) – від 15/28 листопада до Різдва Христового",
    "dayOfWeek": "вт",
    "shiftDaysFromEaster": 219
  },
  "20351205": {
    "type": "pist",
    "name": "Різдвяний піст (Пилипівка) – від 15/28 листопада до Різдва Христового",
    "dayOfWeek": "ср",
    "shiftDaysFromEaster": 220
  },
  "20351206": {
    "type": "pist",
    "name": "Різдвяний піст (Пилипівка) – від 15/28 листопада до Різдва Христового",
    "dayOfWeek": "чт",
    "shiftDaysFromEaster": 221
  },
  "20351207": {
    "type": "pist",
    "name": "Різдвяний піст (Пилипівка) – від 15/28 листопада до Різдва Христового",
    "dayOfWeek": "пт",
    "shiftDaysFromEaster": 222
  },
  "20351208": {
    "type": "pist",
    "name": "Різдвяний піст (Пилипівка) – від 15/28 листопада до Різдва Христового",
    "dayOfWeek": "сб",
    "shiftDaysFromEaster": 223
  },
  "20351209": {
    "type": "pist",
    "name": "Різдвяний піст (Пилипівка) – від 15/28 листопада до Різдва Христового",
    "dayOfWeek": "нд",
    "shiftDaysFromEaster": 224
  },
  "20351210": {
    "type": "pist",
    "name": "Різдвяний піст (Пилипівка) – від 15/28 листопада до Різдва Христового",
    "dayOfWeek": "пн",
    "shiftDaysFromEaster": 225
  },
  "20351211": {
    "type": "pist",
    "name": "Різдвяний піст (Пилипівка) – від 15/28 листопада до Різдва Христового",
    "dayOfWeek": "вт",
    "shiftDaysFromEaster": 226
  },
  "20351212": {
    "type": "pist",
    "name": "Різдвяний піст (Пилипівка) – від 15/28 листопада до Різдва Христового",
    "dayOfWeek": "ср",
    "shiftDaysFromEaster": 227
  },
  "20351213": {
    "type": "pist",
    "name": "Різдвяний піст (Пилипівка) – від 15/28 листопада до Різдва Христового",
    "dayOfWeek": "чт",
    "shiftDaysFromEaster": 228
  },
  "20351214": {
    "type": "pist",
    "name": "Різдвяний піст (Пилипівка) – від 15/28 листопада до Різдва Христового",
    "dayOfWeek": "пт",
    "shiftDaysFromEaster": 229
  },
  "20351215": {
    "type": "pist",
    "name": "Різдвяний піст (Пилипівка) – від 15/28 листопада до Різдва Христового",
    "dayOfWeek": "сб",
    "shiftDaysFromEaster": 230
  },
  "20351216": {
    "type": "pist",
    "name": "Різдвяний піст (Пилипівка) – від 15/28 листопада до Різдва Христового",
    "dayOfWeek": "нд",
    "shiftDaysFromEaster": 231
  },
  "20351217": {
    "type": "pist",
    "name": "Різдвяний піст (Пилипівка) – від 15/28 листопада до Різдва Христового",
    "dayOfWeek": "пн",
    "shiftDaysFromEaster": 232
  },
  "20351218": {
    "type": "pist",
    "name": "Різдвяний піст (Пилипівка) – від 15/28 листопада до Різдва Христового",
    "dayOfWeek": "вт",
    "shiftDaysFromEaster": 233
  },
  "20351219": {
    "type": null,
    "name": "Різдвяний піст (Пилипівка) – від 15/28 листопада до Різдва Христового",
    "dayOfWeek": "ср",
    "shiftDaysFromEaster": 234
  },
  "20351220": {
    "type": "pist",
    "name": "Різдвяний піст (Пилипівка) – від 15/28 листопада до Різдва Христового",
    "dayOfWeek": "чт",
    "shiftDaysFromEaster": 235
  },
  "20351221": {
    "type": "pist",
    "name": "Різдвяний піст (Пилипівка) – від 15/28 листопада до Різдва Христового",
    "dayOfWeek": "пт",
    "shiftDaysFromEaster": 236
  },
  "20351222": {
    "type": null,
    "name": "Різдвяний піст (Пилипівка) – від 15/28 листопада до Різдва Христового",
    "dayOfWeek": "сб",
    "shiftDaysFromEaster": 237
  },
  "20351223": {
    "type": "pist",
    "name": "Різдвяний піст (Пилипівка) – від 15/28 листопада до Різдва Христового",
    "dayOfWeek": "нд",
    "shiftDaysFromEaster": 238
  },
  "20351224": {
    "type": "pist",
    "name": "Різдвяний піст (Пилипівка) – від 15/28 листопада до Різдва Христового",
    "dayOfWeek": "пн",
    "shiftDaysFromEaster": 239
  },
  "20351225": {
    "type": "pist",
    "name": "Різдвяний піст (Пилипівка) – від 15/28 листопада до Різдва Христового",
    "dayOfWeek": "вт",
    "shiftDaysFromEaster": 240
  },
  "20351226": {
    "type": "pist",
    "name": "Різдвяний піст (Пилипівка) – від 15/28 листопада до Різдва Христового",
    "dayOfWeek": "ср",
    "shiftDaysFromEaster": 241
  },
  "20351227": {
    "type": "pist",
    "name": "Різдвяний піст (Пилипівка) – від 15/28 листопада до Різдва Христового",
    "dayOfWeek": "чт",
    "shiftDaysFromEaster": 242
  },
  "20351228": {
    "type": "pist",
    "name": "Різдвяний піст (Пилипівка) – від 15/28 листопада до Різдва Христового",
    "dayOfWeek": "пт",
    "shiftDaysFromEaster": 243
  },
  "20351229": {
    "type": "pist",
    "name": "Різдвяний піст (Пилипівка) – від 15/28 листопада до Різдва Христового",
    "dayOfWeek": "сб",
    "shiftDaysFromEaster": 244
  },
  "20351230": {
    "type": "pist",
    "name": "Різдвяний піст (Пилипівка) – від 15/28 листопада до Різдва Христового",
    "dayOfWeek": "нд",
    "shiftDaysFromEaster": 245
  },
  "20351231": {
    "type": "pist",
    "name": "Різдвяний піст (Пилипівка) – від 15/28 листопада до Різдва Христового",
    "dayOfWeek": "пн",
    "shiftDaysFromEaster": 246
  }
}
