{
  "20470101": {
    "isRed": true,
    "dayOfWeek": "вт",
    "shiftDaysFromEaster": -110
  },
  "20470106": {
    "isRed": true,
    "dayOfWeek": "нд",
    "shiftDaysFromEaster": -105
  },
  "20470107": {
    "isRed": true,
    "dayOfWeek": "пн",
    "shiftDaysFromEaster": -104
  },
  "20470108": {
    "isRed": true,
    "dayOfWeek": "вт",
    "shiftDaysFromEaster": -103
  },
  "20470109": {
    "isRed": true,
    "dayOfWeek": "ср",
    "shiftDaysFromEaster": -102
  },
  "20470113": {
    "isRed": true,
    "dayOfWeek": "нд",
    "shiftDaysFromEaster": -98
  },
  "20470114": {
    "isRed": true,
    "dayOfWeek": "пн",
    "shiftDaysFromEaster": -97
  },
  "20470119": {
    "isRed": true,
    "dayOfWeek": "сб",
    "shiftDaysFromEaster": -92
  },
  "20470120": {
    "isRed": true,
    "dayOfWeek": "нд",
    "shiftDaysFromEaster": -91
  },
  "20470127": {
    "isRed": true,
    "dayOfWeek": "нд",
    "shiftDaysFromEaster": -84
  },
  "20470203": {
    "isRed": true,
    "dayOfWeek": "нд",
    "shiftDaysFromEaster": -77
  },
  "20470210": {
    "isRed": true,
    "dayOfWeek": "нд",
    "shiftDaysFromEaster": -70
  },
  "20470212": {
    "isRed": true,
    "dayOfWeek": "вт",
    "shiftDaysFromEaster": -68
  },
  "20470215": {
    "isRed": true,
    "dayOfWeek": "пт",
    "shiftDaysFromEaster": -65
  },
  "20470217": {
    "isRed": true,
    "dayOfWeek": "нд",
    "shiftDaysFromEaster": -63
  },
  "20470224": {
    "isRed": true,
    "dayOfWeek": "нд",
    "shiftDaysFromEaster": -56
  },
  "20470303": {
    "isRed": true,
    "dayOfWeek": "нд",
    "shiftDaysFromEaster": -49
  },
  "20470310": {
    "isRed": true,
    "dayOfWeek": "нд",
    "shiftDaysFromEaster": -42
  },
  "20470317": {
    "isRed": true,
    "dayOfWeek": "нд",
    "shiftDaysFromEaster": -35
  },
  "20470324": {
    "isRed": true,
    "dayOfWeek": "нд",
    "shiftDaysFromEaster": -28
  },
  "20470331": {
    "isRed": true,
    "dayOfWeek": "нд",
    "shiftDaysFromEaster": -21
  },
  "20470407": {
    "isRed": true,
    "dayOfWeek": "нд",
    "shiftDaysFromEaster": -14
  },
  "20470414": {
    "isRed": true,
    "dayOfWeek": "нд",
    "shiftDaysFromEaster": -7
  },
  "20470421": {
    "isRed": true,
    "dayOfWeek": "нд",
    "shiftDaysFromEaster": 0
  },
  "20470422": {
    "isRed": true,
    "dayOfWeek": "пн",
    "shiftDaysFromEaster": 1
  },
  "20470423": {
    "isRed": true,
    "dayOfWeek": "вт",
    "shiftDaysFromEaster": 2
  },
  "20470428": {
    "isRed": true,
    "dayOfWeek": "нд",
    "shiftDaysFromEaster": 7
  },
  "20470505": {
    "isRed": true,
    "dayOfWeek": "нд",
    "shiftDaysFromEaster": 14
  },
  "20470512": {
    "isRed": true,
    "dayOfWeek": "нд",
    "shiftDaysFromEaster": 21
  },
  "20470519": {
    "isRed": true,
    "dayOfWeek": "нд",
    "shiftDaysFromEaster": 28
  },
  "20470526": {
    "isRed": true,
    "dayOfWeek": "нд",
    "shiftDaysFromEaster": 35
  },
  "20470530": {
    "isRed": true,
    "dayOfWeek": "чт",
    "shiftDaysFromEaster": 39
  },
  "20470602": {
    "isRed": true,
    "dayOfWeek": "нд",
    "shiftDaysFromEaster": 42
  },
  "20470609": {
    "isRed": true,
    "dayOfWeek": "нд",
    "shiftDaysFromEaster": 49
  },
  "20470610": {
    "isRed": true,
    "dayOfWeek": "пн",
    "shiftDaysFromEaster": 50
  },
  "20470616": {
    "isRed": true,
    "dayOfWeek": "нд",
    "shiftDaysFromEaster": 56
  },
  "20470620": {
    "isRed": true,
    "dayOfWeek": "чт",
    "shiftDaysFromEaster": 60
  },
  "20470623": {
    "isRed": true,
    "dayOfWeek": "нд",
    "shiftDaysFromEaster": 63
  },
  "20470628": {
    "isRed": true,
    "dayOfWeek": "пт",
    "shiftDaysFromEaster": 68
  },
  "20470630": {
    "isRed": true,
    "dayOfWeek": "нд",
    "shiftDaysFromEaster": 70
  },
  "20470707": {
    "isRed": true,
    "dayOfWeek": "нд",
    "shiftDaysFromEaster": 77
  },
  "20470712": {
    "isRed": true,
    "dayOfWeek": "пт",
    "shiftDaysFromEaster": 82
  },
  "20470714": {
    "isRed": true,
    "dayOfWeek": "нд",
    "shiftDaysFromEaster": 84
  },
  "20470721": {
    "isRed": true,
    "dayOfWeek": "нд",
    "shiftDaysFromEaster": 91
  },
  "20470728": {
    "isRed": true,
    "dayOfWeek": "нд",
    "shiftDaysFromEaster": 98
  },
  "20470804": {
    "isRed": true,
    "dayOfWeek": "нд",
    "shiftDaysFromEaster": 105
  },
  "20470811": {
    "isRed": true,
    "dayOfWeek": "нд",
    "shiftDaysFromEaster": 112
  },
  "20470818": {
    "isRed": true,
    "dayOfWeek": "нд",
    "shiftDaysFromEaster": 119
  },
  "20470819": {
    "isRed": true,
    "dayOfWeek": "пн",
    "shiftDaysFromEaster": 120
  },
  "20470825": {
    "isRed": true,
    "dayOfWeek": "нд",
    "shiftDaysFromEaster": 126
  },
  "20470828": {
    "isRed": true,
    "dayOfWeek": "ср",
    "shiftDaysFromEaster": 129
  },
  "20470901": {
    "isRed": true,
    "dayOfWeek": "нд",
    "shiftDaysFromEaster": 133
  },
  "20470908": {
    "isRed": true,
    "dayOfWeek": "нд",
    "shiftDaysFromEaster": 140
  },
  "20470911": {
    "isRed": true,
    "dayOfWeek": "ср",
    "shiftDaysFromEaster": 143
  },
  "20470915": {
    "isRed": true,
    "dayOfWeek": "нд",
    "shiftDaysFromEaster": 147
  },
  "20470921": {
    "isRed": true,
    "dayOfWeek": "сб",
    "shiftDaysFromEaster": 153
  },
  "20470922": {
    "isRed": true,
    "dayOfWeek": "нд",
    "shiftDaysFromEaster": 154
  },
  "20470927": {
    "isRed": true,
    "dayOfWeek": "пт",
    "shiftDaysFromEaster": 159
  },
  "20470929": {
    "isRed": true,
    "dayOfWeek": "нд",
    "shiftDaysFromEaster": 161
  },
  "20471006": {
    "isRed": true,
    "dayOfWeek": "нд",
    "shiftDaysFromEaster": 168
  },
  "20471013": {
    "isRed": true,
    "dayOfWeek": "нд",
    "shiftDaysFromEaster": 175
  },
  "20471014": {
    "isRed": true,
    "dayOfWeek": "пн",
    "shiftDaysFromEaster": 176
  },
  "20471020": {
    "isRed": true,
    "dayOfWeek": "нд",
    "shiftDaysFromEaster": 182
  },
  "20471027": {
    "isRed": true,
    "dayOfWeek": "нд",
    "shiftDaysFromEaster": 189
  },
  "20471103": {
    "isRed": true,
    "dayOfWeek": "нд",
    "shiftDaysFromEaster": 196
  },
  "20471110": {
    "isRed": true,
    "dayOfWeek": "нд",
    "shiftDaysFromEaster": 203
  },
  "20471117": {
    "isRed": true,
    "dayOfWeek": "нд",
    "shiftDaysFromEaster": 210
  },
  "20471121": {
    "isRed": true,
    "dayOfWeek": "чт",
    "shiftDaysFromEaster": 214
  },
  "20471124": {
    "isRed": true,
    "dayOfWeek": "нд",
    "shiftDaysFromEaster": 217
  },
  "20471201": {
    "isRed": true,
    "dayOfWeek": "нд",
    "shiftDaysFromEaster": 224
  },
  "20471204": {
    "isRed": true,
    "dayOfWeek": "ср",
    "shiftDaysFromEaster": 227
  },
  "20471208": {
    "isRed": true,
    "dayOfWeek": "нд",
    "shiftDaysFromEaster": 231
  },
  "20471215": {
    "isRed": true,
    "dayOfWeek": "нд",
    "shiftDaysFromEaster": 238
  },
  "20471219": {
    "isRed": true,
    "dayOfWeek": "чт",
    "shiftDaysFromEaster": 242
  },
  "20471222": {
    "isRed": true,
    "dayOfWeek": "нд",
    "shiftDaysFromEaster": 245
  },
  "20471229": {
    "isRed": true,
    "dayOfWeek": "нд",
    "shiftDaysFromEaster": 252
  }
}
